mem0/__init__.py
mem0/client/__init__.py
mem0/client/main.py
mem0/configs/__init__.py
mem0/configs/base.py
mem0/configs/enums.py
mem0/configs/prompts.py
mem0/configs/embeddings/__init__.py
mem0/configs/embeddings/base.py
mem0/configs/llms/__init__.py
mem0/configs/llms/base.py
mem0/configs/vector_stores/__init__.py
mem0/configs/vector_stores/azure_ai_search.py
mem0/configs/vector_stores/chroma.py
mem0/configs/vector_stores/elasticsearch.py
mem0/configs/vector_stores/faiss.py
mem0/configs/vector_stores/langchain.py
mem0/configs/vector_stores/milvus.py
mem0/configs/vector_stores/opensearch.py
mem0/configs/vector_stores/pgvector.py
mem0/configs/vector_stores/pinecone.py
mem0/configs/vector_stores/qdrant.py
mem0/configs/vector_stores/redis.py
mem0/configs/vector_stores/supabase.py
mem0/configs/vector_stores/upstash_vector.py
mem0/configs/vector_stores/vertex_ai_vector_search.py
mem0/configs/vector_stores/weaviate.py
mem0/embeddings/__init__.py
mem0/embeddings/aws_bedrock.py
mem0/embeddings/azure_openai.py
mem0/embeddings/base.py
mem0/embeddings/configs.py
mem0/embeddings/gemini.py
mem0/embeddings/huggingface.py
mem0/embeddings/langchain.py
mem0/embeddings/lmstudio.py
mem0/embeddings/mock.py
mem0/embeddings/ollama.py
mem0/embeddings/openai.py
mem0/embeddings/together.py
mem0/embeddings/vertexai.py
mem0/graphs/configs.py
mem0/graphs/tools.py
mem0/graphs/utils.py
mem0/llms/__init__.py
mem0/llms/anthropic.py
mem0/llms/aws_bedrock.py
mem0/llms/azure_openai.py
mem0/llms/azure_openai_structured.py
mem0/llms/base.py
mem0/llms/configs.py
mem0/llms/deepseek.py
mem0/llms/gemini.py
mem0/llms/groq.py
mem0/llms/langchain.py
mem0/llms/litellm.py
mem0/llms/lmstudio.py
mem0/llms/ollama.py
mem0/llms/openai.py
mem0/llms/openai_structured.py
mem0/llms/sarvam.py
mem0/llms/together.py
mem0/llms/xai.py
mem0/llms/utils/__init__.py
mem0/llms/utils/functions.py
mem0/memory/__init__.py
mem0/memory/base.py
mem0/memory/graph_memory.py
mem0/memory/main.py
mem0/memory/memgraph_memory.py
mem0ai-0.1.107.post1.dist-info/METADATA
mem0ai-0.1.107.post1.dist-info/WHEEL
mem0ai-0.1.107.post1.dist-info/licenses/LICENSE
mem0ai-0.1.107.post1.dist-info/RECORD
